flask_githubapplication/__init__.py
flask_githubapplication/core.py
Flask_GitHubApplication-1.2.0.dist-info/LICENSE
Flask_GitHubApplication-1.2.0.dist-info/METADATA
Flask_GitHubApplication-1.2.0.dist-info/WHEEL
Flask_GitHubApplication-1.2.0.dist-info/top_level.txt
Flask_GitHubApplication-1.2.0.dist-info/RECORD
