Metadata-Version: 2.1
Name: Flask-GitHubApplication
Version: 1.2.0
Summary: Flask extension for creating Github Apps
Home-page: https://github.com/ffalor/flask-githubapplication
Author: Frank Falor
Author-email: ffalorjr@outlook.com
License: GNU3
Project-URL: Bug Tracker, https://github.com/ffalor/flask-githubapplicatio/issues
Platform: UNKNOWN
Classifier: License :: OSI Approved :: MIT License
Classifier: Framework :: Flask
Classifier: Programming Language :: Python
Classifier: Programming Language :: Python :: 3.6
Classifier: Programming Language :: Python :: 3.7
Classifier: Programming Language :: Python :: 3.8
Classifier: Environment :: Web Environment
Classifier: Intended Audience :: Developers
Classifier: Operating System :: OS Independent
Classifier: Topic :: Internet :: WWW/HTTP :: Dynamic Content
Classifier: Topic :: Software Development :: Libraries :: Python Modules
License-File: LICENSE
Requires-Dist: flask (==2.0.1)
Requires-Dist: ghapi (==0.1.19)
Requires-Dist: requests (==2.22.0)
Requires-Dist: pyjwt[crypto] (==2.1.0)
